lazyjson.py
lazyjson-0.0.1.dist-info/LICENSE
lazyjson-0.0.1.dist-info/METADATA
lazyjson-0.0.1.dist-info/WHEEL
lazyjson-0.0.1.dist-info/top_level.txt
lazyjson-0.0.1.dist-info/RECORD
