Metadata-Version: 2.1
Name: lazyjson
Version: 0.0.1
Summary: Encode existing JSON strings within new JSON documents efficiently...ish
Home-page: https://github.com/willstott101/lazyjson
Author: Will Stott
Author-email: willstott101@gmail.com
License: MIT
Project-URL: Source, https://github.com/willstott101/lazyjson
Platform: UNKNOWN
Classifier: Intended Audience :: Developers
Classifier: License :: OSI Approved :: MIT License
Classifier: Operating System :: OS Independent
Classifier: Programming Language :: Python
Classifier: Programming Language :: Python :: 3
Classifier: Topic :: Software Development :: Libraries :: Python Modules
Requires-Python: >=3.5
